patronus/__init__.py
patronus/config.py
patronus/exceptions.py
patronus/init.py
patronus/retry.py
patronus/utils.py
patronus/api/__init__.py
patronus/api/api_client.py
patronus/api/api_client_base.py
patronus/api/api_types.py
patronus/context/__init__.py
patronus/context/context_utils.py
patronus/datasets/__init__.py
patronus/datasets/datasets.py
patronus/datasets/remote.py
patronus/evals/__init__.py
patronus/evals/context.py
patronus/evals/evaluators.py
patronus/evals/exporter.py
patronus/evals/types.py
patronus/experiments/__init__.py
patronus/experiments/adapters.py
patronus/experiments/async_utils.py
patronus/experiments/experiment.py
patronus/experiments/reporter.py
patronus/experiments/tqdm.py
patronus/experiments/types.py
patronus/integrations/__init__.py
patronus/integrations/instrumenter.py
patronus/integrations/otel.py
patronus/integrations/pydantic_ai.py
patronus/pat_client/__init__.py
patronus/pat_client/client_async.py
patronus/pat_client/client_sync.py
patronus/pat_client/container.py
patronus/prompts/__init__.py
patronus/prompts/clients.py
patronus/prompts/models.py
patronus/prompts/templating.py
patronus/tracing/__init__.py
patronus/tracing/attributes.py
patronus/tracing/decorators.py
patronus/tracing/exporters.py
patronus/tracing/logger.py
patronus/tracing/tracer.py
patronus-0.21.0.dist-info/METADATA
patronus-0.21.0.dist-info/WHEEL
patronus-0.21.0.dist-info/RECORD
