Metadata-Version: 2.4
Name: patronus
Version: 0.21.0
Summary: Patronus Python SDK
Project-URL: Homepage, https://www.patronus.ai
Project-URL: Documentation, https://docs.patronus.ai
Project-URL: Repository, https://github.com/patronus-ai/patronus-py
Author-email: Jędrzej Rosłaniec <jedrzej@patronus.ai>, Micheal Jaszczuk <michael@patronus.ai>
License-Expression: MIT
Requires-Python: >=3.9
Requires-Dist: httpx>=0.27.0
Requires-Dist: opentelemetry-api>=1.31.1
Requires-Dist: opentelemetry-exporter-otlp>=1.31.0
Requires-Dist: opentelemetry-sdk>=1.31.1
Requires-Dist: patronus-api>=0.2.0
Requires-Dist: pydantic-settings>=2.4.0
Requires-Dist: pydantic>=2.8.2
Requires-Dist: pyyaml>=6.0.2
Requires-Dist: tqdm>=4.66.5
Requires-Dist: typing-extensions>=4.12.2
Provides-Extra: examples
Requires-Dist: patronus-examples==0.21.0; extra == 'examples'
Provides-Extra: experiments
Requires-Dist: pandas>=2.0.0; extra == 'experiments'
